<?xml version="1.0" encoding="utf-8"?>
<cheddar_gpu>
 <DAG_list>
  <DAG>
   <id>1</id>
   <kernel_count>3</kernel_count>
   <stream>1</stream>
   <kernels>
    <kernel>
     <id>1</id>
     <block_count>8</block_count>
     <block_size>1</block_size>
     <period>30</period>
     <capacity>2</capacity>
     <deadline>30</deadline>
    </kernel>
    <kernel>
     <id>2</id>
     <block_count>8</block_count>
     <block_size>1</block_size>
     <period>30</period>
     <capacity>1</capacity>
     <deadline>30</deadline>
    </kernel>
    <kernel>
     <id>3</id>
     <block_count>8</block_count>
     <block_size>1</block_size>
     <period>462</period>
     <capacity>19</capacity>
     <deadline>462</deadline>
    </kernel>
   </kernels>
  </DAG>
  <DAG>
   <id>2</id>
   <kernel_count>4</kernel_count>
   <stream>2</stream>
   <kernels>
    <kernel>
     <id>1</id>
     <block_count>8</block_count>
     <block_size>1</block_size>
     <period>30</period>
     <capacity>1</capacity>
     <deadline>30</deadline>
    </kernel>
    <kernel>
     <id>2</id>
     <block_count>8</block_count>
     <block_size>1</block_size>
     <period>30</period>
     <capacity>4</capacity>
     <deadline>30</deadline>
    </kernel>
    <kernel>
     <id>3</id>
     <block_count>8</block_count>
     <block_size>1</block_size>
     <period>30</period>
     <capacity>1</capacity>
     <deadline>30</deadline>
    </kernel>
    <kernel>
     <id>4</id>
     <block_count>8</block_count>
     <block_size>1</block_size>
     <period>210</period>
     <capacity>111</capacity>
     <deadline>210</deadline>
    </kernel>
   </kernels>
  </DAG>
 </DAG_list>
 <TPC_list>
  <TPC>
   <id>1</id>
   <max_block_size>256</max_block_size>
  </TPC>
  <TPC>
   <id>2</id>
   <max_block_size>512</max_block_size>
  </TPC>
 </TPC_list>
 <stream_TPC_map>
  <assigned_TPCs>
   <TPC>
    <id>1</id>
    <max_block_size>256</max_block_size>
   </TPC>
  </assigned_TPCs>
  <assigned_TPCs>
   <TPC>
    <id>2</id>
    <max_block_size>512</max_block_size>
   </TPC>
  </assigned_TPCs>
  <assigned_TPCs>
   <TPC>
    <id>2</id>
    <max_block_size>512</max_block_size>
   </TPC>
  </assigned_TPCs>
 </stream_TPC_map>
 <TPC_count>2</TPC_count>
</cheddar_gpu>

